bgeditor/__init__.py
bgeditor/common/__init__.py
bgeditor/common/image_helper.py
bgeditor/common/utils.py
bgeditor/dao/AutoEffect.py
bgeditor/dao/Component.py
bgeditor/dao/ComponentVer2.py
bgeditor/dao/FFmpeg.py
bgeditor/dao/FootageController.py
bgeditor/dao/FootageHelper.py
bgeditor/dao/Lyric.py
bgeditor/dao/LyricStatic.py
bgeditor/dao/LyricVer2.py
bgeditor/dao/Matrix.py
bgeditor/dao/MusicHelper.py
bgeditor/dao/RenderHelper.py
bgeditor/dao/SourceDataHelper.py
bgeditor/dao/Summon.py
bgeditor/dao/TextListComp.py
bgeditor/dao/__init__.py
coolbg-3.178.dist-info/METADATA
coolbg-3.178.dist-info/WHEEL
coolbg-3.178.dist-info/top_level.txt
coolbg-3.178.dist-info/RECORD
