Metadata-Version: 2.1
Name: coolbg
Version: 3.178
Summary: A Des of coolbg
Home-page: https://github.com/vtandroid/dokr
Author: Thanh Hoa
Author-email: thanhhoakhmt1@gmail.com
Classifier: Programming Language :: Python :: 3
Classifier: License :: OSI Approved :: MIT License
Classifier: Operating System :: OS Independent
Requires-Dist: requests==2.25.1
Requires-Dist: numpy
Requires-Dist: moviepy
Requires-Dist: Pillow==9.5.0
Requires-Dist: youtube_dl
Requires-Dist: gbak
Requires-Dist: yt_dlp
